tgtoolsinsta/__init__.py
tgtoolsinsta-0.0.8.dist-info/LICENSE
tgtoolsinsta-0.0.8.dist-info/METADATA
tgtoolsinsta-0.0.8.dist-info/WHEEL
tgtoolsinsta-0.0.8.dist-info/top_level.txt
tgtoolsinsta-0.0.8.dist-info/RECORD
