Metadata-Version: 2.1
Name: tgtoolsinsta
Version: 0.0.8
Summary: INSTAGRAM ID AND POST-ID SCRAPER 
Author: T G
Author-email: mail2tgtools@gmail.com
Keywords: Instagram,userid
Classifier: Development Status :: 1 - Planning
Classifier: Intended Audience :: Developers
Classifier: Programming Language :: Python :: 3
Classifier: Operating System :: Unix
Classifier: Operating System :: MacOS :: MacOS X
Classifier: Operating System :: Microsoft :: Windows
License-File: LICENSE
Requires-Dist: requests
